{"data": [{"comment": null, "le": 128, "prefix": "2402:28c0:fff4::", "ge": null, "max_length": 128, "length": 48, "exact": false}, {"comment": null, "le": 128, "prefix": "2404:f4c0:e010::", "ge": null, "max_length": 128, "length": 44, "exact": false}, {"comment": null, "le": 128, "prefix": "2406:840:e400::", "ge": null, "max_length": 128, "length": 44, "exact": false}, {"comment": null, "le": 128, "prefix": "2602:feda:bb0::", "ge": null, "max_length": 128, "length": 44, "exact": false}, {"comment": null, "le": 128, "prefix": "2a07:1c44:9600::", "ge": null, "max_length": 128, "length": 40, "exact": false}, {"comment": null, "le": 128, "prefix": "2a0e:b107:1e0::", "ge": null, "max_length": 128, "length": 44, "exact": false}, {"comment": null, "le": 128, "prefix": "2a0e:b107:580::", "ge": null, "max_length": 128, "length": 44, "exact": false}, {"comment": null, "le": 128, "prefix": "2a0e:b107:5c3::", "ge": null, "max_length": 128, "length": 48, "exact": false}], "ts": 1606676455}