{"data": [{"comment": null, "le": 128, "prefix": "2001:678:c4c::", "ge": null, "max_length": 128, "length": 48, "exact": false}, {"comment": null, "le": 128, "prefix": "2602:809:3000::", "ge": 48, "max_length": 128, "length": 47, "exact": false}, {"comment": null, "le": 128, "prefix": "2a06:e881:4201::", "ge": null, "max_length": 128, "length": 48, "exact": false}, {"comment": null, "le": 128, "prefix": "2a09:11c0:130::", "ge": null, "max_length": 128, "length": 44, "exact": false}, {"comment": null, "le": 128, "prefix": "2a0c:9a40:1022::", "ge": null, "max_length": 128, "length": 48, "exact": false}, {"comment": null, "le": 128, "prefix": "2a0c:9a40:8101::", "ge": null, "max_length": 128, "length": 48, "exact": false}, {"comment": null, "le": 128, "prefix": "2a0c:9a40:8104::", "ge": 48, "max_length": 128, "length": 47, "exact": false}, {"comment": null, "le": 128, "prefix": "2a0c:9a40:8110::", "ge": null, "max_length": 128, "length": 44, "exact": false}, {"comment": null, "le": 128, "prefix": "2a0c:9a40:8130::", "ge": null, "max_length": 128, "length": 44, "exact": false}, {"comment": null, "le": 128, "prefix": "2a0c:9a40:c000::", "ge": null, "max_length": 128, "length": 36, "exact": false}, {"comment": null, "le": 128, "prefix": "2a0c:9a47::", "ge": null, "max_length": 128, "length": 44, "exact": false}, {"comment": null, "le": 128, "prefix": "2a0e:7d40::", "ge": null, "max_length": 128, "length": 29, "exact": false}, {"comment": null, "le": 128, "prefix": "2a0e:8f00:fe00::", "ge": 48, "max_length": 128, "length": 47, "exact": false}, {"comment": null, "le": 128, "prefix": "2a0e:8f00:fe04::", "ge": 48, "max_length": 128, "length": 46, "exact": false}], "ts": 1613340042}