{"data": [{"status": "ok", "looking_glass": "", "route_server": "", "info_ratio": "Heavy Inbound", "id": 19949, "policy_ratio": false, "info_unicast": true, "policy_general": "Open", "website": "http://www.flixtel.in", "allow_ixp_update": true, "updated": "2020-10-26T09:31:26Z", "info_traffic": "1-5Gbps", "info_multicast": true, "asn": 138768, "policy_locations": "Not Required", "name": "Flixtel India", "info_scope": "Global", "notes": "", "created": "2019-05-31T09:18:15Z", "org_id": 22988, "policy_url": "", "info_never_via_route_servers": false, "info_type": "Cable/DSL/ISP", "policy_contracts": "Not Required", "info_prefixes6": 2, "aka": "NetLayer", "info_prefixes4": 100, "info_ipv6": true, "irr_as_set": ""}], "ts": 1606650321}