{"data": [{"status": "ok", "looking_glass": "", "route_server": "", "netixlan_updated": "2021-01-31T00:03:23Z", "info_ratio": "Mostly Inbound", "id": 23673, "policy_ratio": false, "info_unicast": false, "policy_general": "Selective", "website": "http://as140731.bairuo.top", "allow_ixp_update": false, "updated": "2021-01-30T08:01:29Z", "netfac_updated": "2020-07-17T09:16:27Z", "info_traffic": "20-100Mbps", "info_multicast": false, "asn": 140731, "policy_locations": "Preferred", "name": "TOHU Public Internet", "info_scope": "Global", "notes": "", "created": "2020-06-21T01:29:08Z", "org_id": 26462, "policy_url": "https://as140731.bairuo.top", "info_never_via_route_servers": false, "poc_updated": "2020-08-14T12:07:09Z", "info_type": "Educational/Research", "policy_contracts": "Not Required", "info_prefixes6": 20, "aka": "", "info_prefixes4": 20, "info_ipv6": true, "irr_as_set": "RIPE::AS-TOHUNET"}], "ts": 1613871087}