{"data": [{"status": "ok", "looking_glass": "", "route_server": "", "netixlan_updated": "2020-06-29T19:43:55Z", "info_ratio": "Heavy Outbound", "id": 21465, "policy_ratio": false, "info_unicast": false, "policy_general": "Open", "website": "", "allow_ixp_update": true, "updated": "2020-06-29T19:52:04Z", "netfac_updated": "2020-06-29T19:53:32Z", "info_traffic": "20-100Mbps", "info_multicast": false, "asn": 207852, "policy_locations": "Not Required", "name": "Y525", "info_scope": "Global", "notes": "", "created": "2019-11-17T07:18:39Z", "org_id": 24390, "policy_url": "", "info_never_via_route_servers": false, "poc_updated": "2019-12-05T06:24:30Z", "info_type": "Educational/Research", "policy_contracts": "Not Required", "info_prefixes6": 2, "aka": "", "info_prefixes4": 0, "info_ipv6": true, "irr_as_set": "AS-Y525"}], "ts": 1613871084}