{"data": [{"status": "ok", "looking_glass": "https://lg.as212987.org/", "route_server": "", "info_ratio": "Balanced", "id": 23844, "policy_ratio": false, "info_unicast": false, "policy_general": "Open", "website": "https://www.as212987.org/", "allow_ixp_update": false, "updated": "2020-10-25T05:11:12Z", "info_traffic": "20-50Gbps", "info_multicast": false, "asn": 212987, "policy_locations": "Preferred", "name": "NekoCloud Solutions", "info_scope": "Global", "notes": "Everyone with Free Transit or Peering is welcome. Please Write us an Email if you wanna share Transit/Peering at one of our Public Peering Points.", "created": "2020-07-06T20:05:20Z", "org_id": 26607, "policy_url": "https://www.as212987.org/", "info_never_via_route_servers": false, "info_type": "NSP", "policy_contracts": "Not Required", "info_prefixes6": 100, "aka": "Squid Network", "info_prefixes4": 100, "info_ipv6": true, "irr_as_set": "RIPE::AS-SQUIDNETWORK"}], "ts": 1610683231}